MRCpy/__init__.py
MRCpy/amrc.py
MRCpy/base_mrc.py
MRCpy/cmrc.py
MRCpy/dwgcs.py
MRCpy/mrc.py
MRCpy/datasets/__init__.py
MRCpy/datasets/load.py
MRCpy/datasets/data/comp-vs-sci_Test.csv
MRCpy/datasets/data/comp-vs-sci_Train.csv
MRCpy/datasets/data/comp-vs-sci_shortTest.csv
MRCpy/datasets/data/comp-vs-sci_shortTrain.csv
MRCpy/datasets/data/comp-vs-talk_Test.csv
MRCpy/datasets/data/comp-vs-talk_Train.csv
MRCpy/datasets/data/credit.csv
MRCpy/datasets/data/diabetes.csv
MRCpy/datasets/data/ecoli.csv
MRCpy/datasets/data/glass.csv
MRCpy/datasets/data/haberman.csv
MRCpy/datasets/data/indianLiverPatient.csv
MRCpy/datasets/data/iris.csv
MRCpy/datasets/data/letter-recognition.csv
MRCpy/datasets/data/mammographic.csv
MRCpy/datasets/data/optdigits.csv
MRCpy/datasets/data/rec-vs-sci_Test.csv
MRCpy/datasets/data/rec-vs-sci_Train.csv
MRCpy/datasets/data/rec-vs-talk_Test.csv
MRCpy/datasets/data/rec-vs-talk_Train.csv
MRCpy/datasets/data/redwine.csv
MRCpy/datasets/data/sci-vs-talk_Test.csv
MRCpy/datasets/data/sci-vs-talk_Train.csv
MRCpy/datasets/data/segment.csv
MRCpy/datasets/data/usenet2.csv
MRCpy/datasets/descr/adult.rst
MRCpy/datasets/descr/catsvsdogs_features_resnet18.rst
MRCpy/datasets/descr/credit.rst
MRCpy/datasets/descr/diabetes.rst
MRCpy/datasets/descr/ecoli.rst
MRCpy/datasets/descr/glass.rst
MRCpy/datasets/descr/haberman.rst
MRCpy/datasets/descr/indianLiverPatient.rst
MRCpy/datasets/descr/iris.rst
MRCpy/datasets/descr/letter-recognition.rst
MRCpy/datasets/descr/mammographic.rst
MRCpy/datasets/descr/mnist_features_resnet18.rst
MRCpy/datasets/descr/optdigits.rst
MRCpy/datasets/descr/redwine.rst
MRCpy/datasets/descr/satellite.rst
MRCpy/datasets/descr/segment.rst
MRCpy/datasets/descr/usenet2.rst
MRCpy/datasets/descr/vehicle.rst
MRCpy/datasets/descr/yearbook.rst
MRCpy/datasets/descr/yearbook_features_resnet18.rst
MRCpy/phi/__init__.py
MRCpy/phi/base_phi.py
MRCpy/phi/random_fourier_phi.py
MRCpy/phi/random_relu_phi.py
MRCpy/phi/threshold_phi.py
MRCpy/solvers/__init__.py
MRCpy-2.3.0.dist-info/METADATA
MRCpy-2.3.0.dist-info/WHEEL
MRCpy-2.3.0.dist-info/top_level.txt
MRCpy-2.3.0.dist-info/RECORD
