Metadata-Version: 2.1
Name: MRCpy
Version: 2.3.0
Summary: Library for minimax risk classifiers
Home-page: https://github.com/MachineLearningBCAM/MRCpy
Author-email: Kartheek Bondugula <kbondugula@bcamath.org>
Project-URL: Homepage, https://github.com/MachineLearningBCAM/MRCpy
Project-URL: Issues, https://github.com/MachineLearningBCAM/MRCpy/issues
Classifier: Programming Language :: Python :: 3.8
Classifier: Programming Language :: Python :: 3.9
Classifier: Programming Language :: Python :: 3.10
Classifier: Programming Language :: Python :: 3.11
Classifier: Operating System :: OS Independent
Requires-Python: >=3.8
Requires-Dist: numpy (>=1.19)
Requires-Dist: scipy (>=1.4.1)
Requires-Dist: scikit-learn (>=0.22)
Requires-Dist: cvxpy (>=1.1)
Requires-Dist: gurobipy
